shopify_sync/__init__.py
shopify_sync/admin.py
shopify_sync/apps.py
shopify_sync/encoders.py
shopify_sync/handlers.py
shopify_sync/migrations/0001_initial.py
shopify_sync/migrations/0002_auto_20181220_1714.py
shopify_sync/migrations/0002_auto_20190107_1622.py
shopify_sync/migrations/0003_merge_20190107_1818.py
shopify_sync/migrations/0004_auto_20190621_0852.py
shopify_sync/migrations/0005_remove_customer_default_address.py
shopify_sync/migrations/0006_auto_20190712_0702.py
shopify_sync/migrations/0007_order_shipping_address.py
shopify_sync/migrations/0008_order_fulfillments.py
shopify_sync/migrations/0009_auto_20190918_1508.py
shopify_sync/migrations/0010_auto_20230222_1647.py
shopify_sync/migrations/0011_auto_20240806_1405.py
shopify_sync/migrations/__init__.py
shopify_sync/models/__init__.py
shopify_sync/models/address.py
shopify_sync/models/base.py
shopify_sync/models/carrier_service.py
shopify_sync/models/collect.py
shopify_sync/models/custom_collection.py
shopify_sync/models/customer.py
shopify_sync/models/image.py
shopify_sync/models/line_item.py
shopify_sync/models/metafield.py
shopify_sync/models/option.py
shopify_sync/models/order.py
shopify_sync/models/product.py
shopify_sync/models/script_tag.py
shopify_sync/models/session.py
shopify_sync/models/shop.py
shopify_sync/models/smart_collection.py
shopify_sync/models/variant.py
shopify_sync/models/webhook.py
shopify_sync/tests/__init__.py
shopify_sync/tests/recipes.py
shopify_sync/tests/test_collection_sync.py
shopify_sync/tests/test_helpers.py
shopify_sync/tests/test_json_encoding.py
shopify_sync/tests/test_pagination.py
shopify_sync/tests/test_product_sync.py
shopify_sync/tests/test_product_tags.py
shopify_sync/tests/urls.py
shopify_sync/tests/fixtures/customcollection_created.json
shopify_sync/tests/fixtures/customcollection_updated.json
shopify_sync/tests/fixtures/product_created.json
shopify_sync/tests/fixtures/product_updated.json
shopify_sync/tests/fixtures/smartcollection_created.json
django_shopify_sync-3.1.1.dist-info/METADATA
django_shopify_sync-3.1.1.dist-info/WHEEL
django_shopify_sync-3.1.1.dist-info/licenses/LICENSE
django_shopify_sync-3.1.1.dist-info/RECORD
