Metadata-Version: 2.4
Name: django-shopify-sync
Version: 3.1.1
Summary: A package for synchronizing Django models with Shopify resources.
Project-URL: Homepage, https://gitlab.com/thelabnyc/django-shopify-sync
Project-URL: Repository, https://gitlab.com/thelabnyc/django-shopify-sync
Author-email: thelab <thelabdev@thelab.co>
License: MIT
License-File: LICENSE
Requires-Python: >=3.11
Requires-Dist: django-shopify-webhook<0.9.0,>=0.8.0
Requires-Dist: django>=4.2
Requires-Dist: jsonfield>=3.1.0
Requires-Dist: shopifyapi<13,>=12.7.0
